setup.py
aws_course_nbd/Binomialdistribution.py
aws_course_nbd/Gaussiandistribution.py
aws_course_nbd/Generaldistribution.py
aws_course_nbd/__init__.py
aws_course_nbd.egg-info/PKG-INFO
aws_course_nbd.egg-info/SOURCES.txt
aws_course_nbd.egg-info/dependency_links.txt
aws_course_nbd.egg-info/not-zip-safe
aws_course_nbd.egg-info/top_level.txt